{"assets/fonts/AlfaSlabOne-Regular.ttf":["assets/fonts/AlfaSlabOne-Regular.ttf"],"assets/fonts/AmaticSC-Bold.ttf":["assets/fonts/AmaticSC-Bold.ttf"],"assets/fonts/AmaticSC-Regular.ttf":["assets/fonts/AmaticSC-Regular.ttf"],"assets/fonts/BalsamiqSans-Bold.ttf":["assets/fonts/BalsamiqSans-Bold.ttf"],"assets/fonts/BalsamiqSans-Italic.ttf":["assets/fonts/BalsamiqSans-Italic.ttf"],"assets/fonts/BalsamiqSans-Regular.ttf":["assets/fonts/BalsamiqSans-Regular.ttf"],"assets/fonts/Caveat-Bold.ttf":["assets/fonts/Caveat-Bold.ttf"],"assets/fonts/Caveat-Medium.ttf":["assets/fonts/Caveat-Medium.ttf"],"assets/fonts/Caveat-Regular.ttf":["assets/fonts/Caveat-Regular.ttf"],"assets/fonts/Caveat-SemiBold.ttf":["assets/fonts/Caveat-SemiBold.ttf"],"assets/fonts/Comfortaa-Bold.ttf":["assets/fonts/Comfortaa-Bold.ttf"],"assets/fonts/Comfortaa-Light.ttf":["assets/fonts/Comfortaa-Light.ttf"],"assets/fonts/Comfortaa-Medium.ttf":["assets/fonts/Comfortaa-Medium.ttf"],"assets/fonts/Comfortaa-Regular.ttf":["assets/fonts/Comfortaa-Regular.ttf"],"assets/fonts/Comfortaa-SemiBold.ttf":["assets/fonts/Comfortaa-SemiBold.ttf"],"assets/fonts/Cookie-Regular.ttf":["assets/fonts/Cookie-Regular.ttf"],"assets/fonts/GloriaHallelujah-Regular.ttf":["assets/fonts/GloriaHallelujah-Regular.ttf"],"assets/fonts/IndieFlower-Regular.ttf":["assets/fonts/IndieFlower-Regular.ttf"],"assets/fonts/Inter-Bold.ttf":["assets/fonts/Inter-Bold.ttf"],"assets/fonts/Inter-ExtraBold.ttf":["assets/fonts/Inter-ExtraBold.ttf"],"assets/fonts/Inter-ExtraLight.ttf":["assets/fonts/Inter-ExtraLight.ttf"],"assets/fonts/Inter-Light.ttf":["assets/fonts/Inter-Light.ttf"],"assets/fonts/Inter-Medium.ttf":["assets/fonts/Inter-Medium.ttf"],"assets/fonts/Inter-Regular.ttf":["assets/fonts/Inter-Regular.ttf"],"assets/fonts/Inter-SemiBold.ttf":["assets/fonts/Inter-SemiBold.ttf"],"assets/fonts/MeowScript-Regular.ttf":["assets/fonts/MeowScript-Regular.ttf"],"assets/fonts/MontserratAlternates-Bold.ttf":["assets/fonts/MontserratAlternates-Bold.ttf"],"assets/fonts/MontserratAlternates-ExtraBold.ttf":["assets/fonts/MontserratAlternates-ExtraBold.ttf"],"assets/fonts/MontserratAlternates-ExtraLight.ttf":["assets/fonts/MontserratAlternates-ExtraLight.ttf"],"assets/fonts/MontserratAlternates-Italic.ttf":["assets/fonts/MontserratAlternates-Italic.ttf"],"assets/fonts/MontserratAlternates-Light.ttf":["assets/fonts/MontserratAlternates-Light.ttf"],"assets/fonts/MontserratAlternates-Medium.ttf":["assets/fonts/MontserratAlternates-Medium.ttf"],"assets/fonts/MontserratAlternates-Regular.ttf":["assets/fonts/MontserratAlternates-Regular.ttf"],"assets/fonts/MontserratAlternates-SemiBold.ttf":["assets/fonts/MontserratAlternates-SemiBold.ttf"],"assets/fonts/Mulish-Bold.ttf":["assets/fonts/Mulish-Bold.ttf"],"assets/fonts/Mulish-ExtraBold.ttf":["assets/fonts/Mulish-ExtraBold.ttf"],"assets/fonts/Mulish-ExtraLight.ttf":["assets/fonts/Mulish-ExtraLight.ttf"],"assets/fonts/Mulish-Italic.ttf":["assets/fonts/Mulish-Italic.ttf"],"assets/fonts/Mulish-Light.ttf":["assets/fonts/Mulish-Light.ttf"],"assets/fonts/Mulish-Medium.ttf":["assets/fonts/Mulish-Medium.ttf"],"assets/fonts/Mulish-Regular.ttf":["assets/fonts/Mulish-Regular.ttf"],"assets/fonts/Mulish-SemiBold.ttf":["assets/fonts/Mulish-SemiBold.ttf"],"assets/fonts/Quicksand-Bold.ttf":["assets/fonts/Quicksand-Bold.ttf"],"assets/fonts/Quicksand-Medium.ttf":["assets/fonts/Quicksand-Medium.ttf"],"assets/fonts/Quicksand-Regular.ttf":["assets/fonts/Quicksand-Regular.ttf"],"assets/fonts/ReadexPro-Bold.ttf":["assets/fonts/ReadexPro-Bold.ttf"],"assets/fonts/ReadexPro-ExtraLight.ttf":["assets/fonts/ReadexPro-ExtraLight.ttf"],"assets/fonts/ReadexPro-Light.ttf":["assets/fonts/ReadexPro-Light.ttf"],"assets/fonts/ReadexPro-Medium.ttf":["assets/fonts/ReadexPro-Medium.ttf"],"assets/fonts/ReadexPro-Regular.ttf":["assets/fonts/ReadexPro-Regular.ttf"],"assets/fonts/RedactedScript-Bold.ttf":["assets/fonts/RedactedScript-Bold.ttf"],"assets/fonts/RedactedScript-Light.ttf":["assets/fonts/RedactedScript-Light.ttf"],"assets/fonts/RedactedScript-Regular.ttf":["assets/fonts/RedactedScript-Regular.ttf"],"assets/fonts/Righteous-Regular.ttf":["assets/fonts/Righteous-Regular.ttf"],"assets/fonts/Shalimar-Regular.ttf":["assets/fonts/Shalimar-Regular.ttf"],"assets/images/background_nun.jpg":["assets/images/background_nun.jpg"],"assets/images/bg-001.jpg":["assets/images/bg-001.jpg"],"assets/images/bg-005.jpg":["assets/images/bg-005.jpg"],"assets/images/bg-012.jpg":["assets/images/bg-012.jpg"],"assets/images/bg-016.jpg":["assets/images/bg-016.jpg"],"assets/images/bg-018.jpg":["assets/images/bg-018.jpg"],"assets/images/bg-022.jpg":["assets/images/bg-022.jpg"],"assets/images/bg.jpg":["assets/images/bg.jpg"],"assets/images/header.jpg":["assets/images/header.jpg"],"assets/images/icons/553-5537619_external-link-icon-clipart.png":["assets/images/icons/553-5537619_external-link-icon-clipart.png"],"assets/images/icons/android_studio.png":["assets/images/icons/android_studio.png"],"assets/images/icons/apex.png":["assets/images/icons/apex.png"],"assets/images/icons/bandlab.png":["assets/images/icons/bandlab.png"],"assets/images/icons/bandlab_white.png":["assets/images/icons/bandlab_white.png"],"assets/images/icons/code.png":["assets/images/icons/code.png"],"assets/images/icons/code_white.png":["assets/images/icons/code_white.png"],"assets/images/icons/discord.png":["assets/images/icons/discord.png"],"assets/images/icons/discord_white.png":["assets/images/icons/discord_white.png"],"assets/images/icons/fb.png":["assets/images/icons/fb.png"],"assets/images/icons/fb_white.png":["assets/images/icons/fb_white.png"],"assets/images/icons/flutter.png":["assets/images/icons/flutter.png"],"assets/images/icons/flutter_white.png":["assets/images/icons/flutter_white.png"],"assets/images/icons/github.png":["assets/images/icons/github.png"],"assets/images/icons/github_hovered.png":["assets/images/icons/github_hovered.png"],"assets/images/icons/gitlab.png":["assets/images/icons/gitlab.png"],"assets/images/icons/gitlab_hovered.png":["assets/images/icons/gitlab_hovered.png"],"assets/images/icons/gtav.png":["assets/images/icons/gtav.png"],"assets/images/icons/ig.png":["assets/images/icons/ig.png"],"assets/images/icons/ig_white.png":["assets/images/icons/ig_white.png"],"assets/images/icons/linkd.png":["assets/images/icons/linkd.png"],"assets/images/icons/linkd_white.png":["assets/images/icons/linkd_white.png"],"assets/images/icons/pubg.png":["assets/images/icons/pubg.png"],"assets/images/icons/react.png":["assets/images/icons/react.png"],"assets/images/icons/react_white.png":["assets/images/icons/react_white.png"],"assets/images/icons/soundcloud.png":["assets/images/icons/soundcloud.png"],"assets/images/icons/soundcloud_white.png":["assets/images/icons/soundcloud_white.png"],"assets/images/icons/twitch.png":["assets/images/icons/twitch.png"],"assets/images/icons/twitch_white.png":["assets/images/icons/twitch_white.png"],"assets/images/icons/twitter.png":["assets/images/icons/twitter.png"],"assets/images/icons/twitter_white.png":["assets/images/icons/twitter_white.png"],"assets/images/icons/upwork.png":["assets/images/icons/upwork.png"],"assets/images/icons/upwork_white.png":["assets/images/icons/upwork_white.png"],"assets/images/icons/valorant.png":["assets/images/icons/valorant.png"],"assets/images/icons/vscode.png":["assets/images/icons/vscode.png"],"assets/images/icons/vue.png":["assets/images/icons/vue.png"],"assets/images/icons/vue_white.png":["assets/images/icons/vue_white.png"],"assets/images/icons/yt.png":["assets/images/icons/yt.png"],"assets/images/icons/yt_white.png":["assets/images/icons/yt_white.png"],"assets/images/logo/abik-vaidhya-logo-zip-file.zip":["assets/images/logo/abik-vaidhya-logo-zip-file.zip"],"assets/images/logo/av icon.png":["assets/images/logo/av icon.png"],"assets/images/logo/black_bg.png":["assets/images/logo/black_bg.png"],"assets/images/logo/black_transparent.png":["assets/images/logo/black_transparent.png"],"assets/images/logo/stick_logo_transparent.png":["assets/images/logo/stick_logo_transparent.png"],"assets/images/logo/stick_logo_transparent_grey.png":["assets/images/logo/stick_logo_transparent_grey.png"],"assets/images/logo/white_bg.png":["assets/images/logo/white_bg.png"],"assets/images/logo/white_transparent.png":["assets/images/logo/white_transparent.png"],"assets/images/logo/white_transparent_grey.png":["assets/images/logo/white_transparent_grey.png"],"assets/images/patterns.jpg":["assets/images/patterns.jpg"],"assets/images/profile.jpg":["assets/images/profile.jpg"],"assets/images/profile_1.JPG":["assets/images/profile_1.JPG"],"assets/images/profile_2.JPG":["assets/images/profile_2.JPG"],"assets/images/profile_shot.png":["assets/images/profile_shot.png"],"assets/images/projects/alabbar_enterprises_logo.jpg":["assets/images/projects/alabbar_enterprises_logo.jpg"],"assets/images/projects/brandhouse_logo.jpg":["assets/images/projects/brandhouse_logo.jpg"],"assets/images/projects/cyprus_duty_free_logo.png":["assets/images/projects/cyprus_duty_free_logo.png"],"assets/images/projects/ebt_logo.jpeg":["assets/images/projects/ebt_logo.jpeg"],"assets/images/projects/electronica_logo.jpeg":["assets/images/projects/electronica_logo.jpeg"],"assets/images/projects/fasttrack_logo.png":["assets/images/projects/fasttrack_logo.png"],"assets/images/projects/hah_logo.png":["assets/images/projects/hah_logo.png"],"assets/images/projects/hypercity_logo.jpeg":["assets/images/projects/hypercity_logo.jpeg"],"assets/images/projects/ilg_logo.png":["assets/images/projects/ilg_logo.png"],"assets/images/projects/northern_trails.png":["assets/images/projects/northern_trails.png"],"assets/images/projects/northern_trails_logo.png":["assets/images/projects/northern_trails_logo.png"],"assets/images/projects/original_grey_bg.png":["assets/images/projects/original_grey_bg.png"],"assets/images/projects/pfd_cart_screen.jpg":["assets/images/projects/pfd_cart_screen.jpg"],"assets/images/projects/pfd_logo.png":["assets/images/projects/pfd_logo.png"],"assets/images/projects/pfd_screen.jpg":["assets/images/projects/pfd_screen.jpg"],"assets/images/projects/tim_hortons_logo.png":["assets/images/projects/tim_hortons_logo.png"],"assets/images/projects/vansales_logo.png":["assets/images/projects/vansales_logo.png"],"assets/images/projects/weather_app.png":["assets/images/projects/weather_app.png"],"assets/images/projects/wholisticminds_logo.png":["assets/images/projects/wholisticminds_logo.png"],"assets/images/whiteLinesBG.jpg":["assets/images/whiteLinesBG.jpg"],"packages/cupertino_icons/assets/CupertinoIcons.ttf":["packages/cupertino_icons/assets/CupertinoIcons.ttf"]}